bonobo_selenium/__init__.py
bonobo_selenium/_version.py
bonobo_selenium-0.1.1.dist-info/DESCRIPTION.rst
bonobo_selenium-0.1.1.dist-info/METADATA
bonobo_selenium-0.1.1.dist-info/RECORD
bonobo_selenium-0.1.1.dist-info/WHEEL
bonobo_selenium-0.1.1.dist-info/metadata.json
bonobo_selenium-0.1.1.dist-info/top_level.txt
